gps_data_analyzer/__init__.py
gps_data_analyzer/crs.py
gps_data_analyzer/gps_data.py
gps_data_analyzer/io.py
gps_data_analyzer/plot_utils.py
gps_data_analyzer/raster_analysis.py
gps_data_analyzer/time_analysis.py
gps_data_analyzer/utils.py
GpsDataAnalyzer-0.3.0.dist-info/LICENSE
GpsDataAnalyzer-0.3.0.dist-info/METADATA
GpsDataAnalyzer-0.3.0.dist-info/WHEEL
GpsDataAnalyzer-0.3.0.dist-info/top_level.txt
GpsDataAnalyzer-0.3.0.dist-info/RECORD
